best_route_finder-0.1.0.dist-info/METADATA
best_route_finder-0.1.0.dist-info/WHEEL
best_route_finder/best_route_finder.pyi
best_route_finder/__init__.py
best_route_finder/best_route_finder.pyd
best_route_finder-0.1.0.dist-info/RECORD
