Metadata-Version: 2.1
Name: best-route-finder
Version: 0.1.0
Summary: Library for finding best route in the routing table
Author-email: KRunchPL <krunchfrompoland@gmail.com>
License:                                  Apache License
Requires-Python: >=3.9
Project-URL: repository, https://github.com/KRunchPL/best-route-finder
Project-URL: documentation, https://github.com/KRunchPL/best-route-finder
Project-URL: homepage, https://github.com/KRunchPL/best-route-finder
